JsHanshuShiBianchengZhinan/README.md
JsHanshuShiBianchengZhinan/__init__.py
JsHanshuShiBianchengZhinan/__main__.py
JsHanshuShiBianchengZhinan/file.epub
JsHanshuShiBianchengZhinan/index.html
JsHanshuShiBianchengZhinan/css/__init__.py
JsHanshuShiBianchengZhinan/css/annotations.css
JsHanshuShiBianchengZhinan/css/main.css
JsHanshuShiBianchengZhinan/css/normalize.css
JsHanshuShiBianchengZhinan/css/popup.css
JsHanshuShiBianchengZhinan/font/__init__.py
JsHanshuShiBianchengZhinan/font/fontello.eot
JsHanshuShiBianchengZhinan/font/fontello.svg
JsHanshuShiBianchengZhinan/font/fontello.ttf
JsHanshuShiBianchengZhinan/font/fontello.woff
JsHanshuShiBianchengZhinan/img/__init__.py
JsHanshuShiBianchengZhinan/img/annotator-glyph-sprite.png
JsHanshuShiBianchengZhinan/img/annotator-icon-sprite.png
JsHanshuShiBianchengZhinan/img/apple-touch-icon.png
JsHanshuShiBianchengZhinan/img/cancelfullscreen.png
JsHanshuShiBianchengZhinan/img/close.png
JsHanshuShiBianchengZhinan/img/fullscreen.png
JsHanshuShiBianchengZhinan/img/loader.gif
JsHanshuShiBianchengZhinan/img/menu-icon.png
JsHanshuShiBianchengZhinan/img/save.png
JsHanshuShiBianchengZhinan/img/saved.png
JsHanshuShiBianchengZhinan/img/settings-s.png
JsHanshuShiBianchengZhinan/img/settings.png
JsHanshuShiBianchengZhinan/img/star.png
JsHanshuShiBianchengZhinan/js/__init__.py
JsHanshuShiBianchengZhinan/js/epub.js
JsHanshuShiBianchengZhinan/js/epub.min.js
JsHanshuShiBianchengZhinan/js/epub.min.map
JsHanshuShiBianchengZhinan/js/hooks.min.js
JsHanshuShiBianchengZhinan/js/hooks.min.map
JsHanshuShiBianchengZhinan/js/reader.js
JsHanshuShiBianchengZhinan/js/reader.js.map
JsHanshuShiBianchengZhinan/js/reader.min.js
JsHanshuShiBianchengZhinan/js/reader.min.map
JsHanshuShiBianchengZhinan/js/hooks/__init__.py
JsHanshuShiBianchengZhinan/js/hooks/extensions/__init__.py
JsHanshuShiBianchengZhinan/js/hooks/extensions/highlight.js
JsHanshuShiBianchengZhinan/js/libs/__init__.py
JsHanshuShiBianchengZhinan/js/libs/jquery.min.js
js_hanshu_shi_biancheng_zhinan-2024.3.2.0.dist-info/METADATA
js_hanshu_shi_biancheng_zhinan-2024.3.2.0.dist-info/WHEEL
js_hanshu_shi_biancheng_zhinan-2024.3.2.0.dist-info/entry_points.txt
js_hanshu_shi_biancheng_zhinan-2024.3.2.0.dist-info/top_level.txt
js_hanshu_shi_biancheng_zhinan-2024.3.2.0.dist-info/RECORD
